pymfpatch/__init__.py
pymfpatch/io/__init__.py
pymfpatch/io/parser_utils.py
pymfpatch/utils/__init__.py
pymfpatch/utils/imputer.py
pymfpatch/utils/neuralnetwork.py
pymfpatch/utils/prepfile.py
pymfpatch-1.0.0.dist-info/licenses/LICENSE
pymfpatch-1.0.0.dist-info/METADATA
pymfpatch-1.0.0.dist-info/WHEEL
pymfpatch-1.0.0.dist-info/entry_points.txt
pymfpatch-1.0.0.dist-info/top_level.txt
pymfpatch-1.0.0.dist-info/RECORD
