Metadata-Version: 2.4
Name: pymfpatch
Version: 1.0.0
Summary: Fill missing weather measurements using user-provided ERA5 data and a hybrid GRU + XGBoost approach
Home-page: https://gitlab.com/arep-dev/pymfpatch.git
Author: Alexis SAUVAGEON
Author-email: Your Name <your.email@example.com>
Keywords: weather,Météo-France,ERA5,encoder-decoder,machine learning
Classifier: Programming Language :: Python :: 3
Classifier: License :: OSI Approved :: MIT License
Classifier: Operating System :: OS Independent
Requires-Python: >=3.7
License-File: LICENSE
Dynamic: author
Dynamic: home-page
Dynamic: license-file
Dynamic: requires-python
